spotify_mpd_sync/__init__.py
spotify_mpd_sync/msplaylist/__init__.py
spotify_mpd_sync/msplaylist/authenticate.py
spotify_mpd_sync/msplaylist/spotify.py
spotify_mpd_sync-1.0.2.dist-info/LICENSE.md
spotify_mpd_sync-1.0.2.dist-info/METADATA
spotify_mpd_sync-1.0.2.dist-info/WHEEL
spotify_mpd_sync-1.0.2.dist-info/entry_points.txt
spotify_mpd_sync-1.0.2.dist-info/top_level.txt
spotify_mpd_sync-1.0.2.dist-info/RECORD
