Metadata-Version: 2.1
Name: spotify-mpd-sync
Version: 1.0.2
Summary: Synchronize Spotify Playlist to MPD
Home-page: https://github.com/weskerfoot/Spotify-MPD-Sync
Author: Wesley Kerfoot
Author-email: wes@wesk.tech
License: UNKNOWN
Platform: UNKNOWN
Classifier: Programming Language :: Python :: 3
Classifier: License :: OSI Approved :: MIT License
Classifier: Operating System :: OS Independent
Requires-Dist: spotipy (>=2.4.4)
Requires-Dist: python-mpd2 (>=1.0.0)
Requires-Dist: bottle (>=0.12.16)
Requires-Dist: gevent (>=1.4.0)
